{"frameRate":30,"name":"spherelight","version":"5.5","compatibleVersion":"5.5","armature":[{"type":"Armature","frameRate":30,"name":"spherelight","aabb":{"x":-21.5,"y":-21,"width":43,"height":42},"bone":[{"name":"Layer 1"}],"slot":[{"name":"Layer 1","parent":"Layer 1"}],"skin":[{"slot":[{"name":"Layer 1","display":[{"name":"Shape/shape 12536"},{"name":"Shape/shape 12538"},{"name":"Shape/shape 12540"},{"name":"Shape/shape 12542"},{"name":"Shape/shape 12544"},{"name":"Shape/shape 12546"},{"name":"Shape/shape 12548"},{"name":"Shape/shape 12550"},{"name":"Shape/shape 12552"}]}]}],"animation":[{"duration":8,"fadeInTime":0.3,"name":"spherelight","slot":[{"name":"Layer 1","displayFrame":[{},{"value":1},{"value":2},{"value":3},{"value":4},{"value":5},{"value":6},{"value":7},{"duration":0,"value":8}]}]}],"defaultActions":[{"gotoAndPlay":"spherelight"}]}]}