{"width":256,"imagePath":"Training_3_mc_tex.png","name":"Training_3_mc","SubTexture":[{"width":50,"y":129,"height":50,"name":"1","x":1},{"frameY":-45,"y":129,"frameWidth":65,"frameHeight":47,"width":2,"height":2,"name":"Shape/shape 2308","frameX":0,"x":53},{"frameY":-7,"y":45,"frameWidth":65,"frameHeight":47,"width":65,"height":40,"name":"Shape/shape 2331","frameX":0,"x":66},{"frameY":-19,"y":225,"frameWidth":65,"frameHeight":47,"width":65,"height":28,"name":"Shape/shape 2322","frameX":0,"x":1},{"frameY":-5,"y":181,"frameWidth":65,"frameHeight":47,"width":57,"height":42,"name":"Shape/shape 2334","frameX":-1,"x":1},{"frameY":-43,"y":167,"frameWidth":65,"frameHeight":47,"width":65,"height":4,"name":"Shape/shape 2310","frameX":0,"x":128},{"frameY":-7,"y":87,"frameWidth":65,"frameHeight":47,"width":65,"height":40,"name":"Shape/shape 2324","frameX":0,"x":1},{"frameY":-2,"y":87,"frameWidth":65,"frameHeight":47,"width":59,"height":44,"name":"Shape/shape 2336","frameX":-2,"x":68},{"frameY":-41,"y":159,"frameWidth":65,"frameHeight":47,"width":65,"height":6,"name":"Shape/shape 2312","frameX":0,"x":128},{"frameY":0,"y":1,"frameWidth":65,"frameHeight":47,"width":63,"height":45,"name":"Shape/shape 2338","frameX":-2,"x":1},{"frameY":-6,"y":44,"frameWidth":65,"frameHeight":47,"width":65,"height":41,"name":"Shape/shape 2326","frameX":0,"x":133},{"frameY":-38,"y":101,"frameWidth":65,"frameHeight":47,"width":65,"height":9,"name":"Shape/shape 2314","frameX":0,"x":172},{"frameY":-5,"y":1,"frameWidth":65,"frameHeight":47,"width":65,"height":42,"name":"Shape/shape 2328","frameX":0,"x":66},{"frameY":-35,"y":87,"frameWidth":65,"frameHeight":47,"width":65,"height":12,"name":"Shape/shape 2316","frameX":0,"x":172},{"frameY":-6,"y":1,"frameWidth":65,"frameHeight":47,"width":65,"height":41,"name":"Shape/shape 2329","frameX":0,"x":133},{"frameY":-29,"y":133,"frameWidth":65,"frameHeight":47,"width":65,"height":18,"name":"Shape/shape 2318","frameX":0,"x":53},{"width":36,"y":153,"height":25,"name":"补间 27","x":53},{"frameY":0,"y":180,"frameWidth":36,"frameHeight":25,"width":35,"height":25,"name":"补间 29","frameX":0,"x":98},{"width":36,"y":180,"height":25,"name":"__dbTextures/Training_3_mc/Layer 3_0_12","x":60},{"width":11,"y":123,"height":8,"name":"__dbTextures/Training_3_mc/Layer 3_0_8","x":129},{"frameY":0,"y":87,"frameWidth":36,"frameHeight":25,"width":35,"height":24,"name":"补间 28","frameX":0,"x":135},{"width":35,"y":153,"height":25,"name":"__dbTextures/Training_3_mc/Layer 3_0_63","x":91},{"frameY":0,"y":113,"frameWidth":36,"frameHeight":24,"width":35,"height":24,"name":"__dbTextures/Training_3_mc/Layer 3_0_14","frameX":0,"x":165},{"frameY":0,"y":133,"frameWidth":35,"frameHeight":25,"width":35,"height":24,"name":"补间 41","frameX":0,"x":128},{"width":36,"y":48,"height":25,"name":"__dbTextures/Training_3_mc/Layer 3_0_61","x":1},{"width":11,"y":113,"height":8,"name":"__dbTextures/Training_3_mc/Layer 3_0_57","x":129},{"frameY":0,"y":207,"frameWidth":36,"frameHeight":25,"width":35,"height":25,"name":"__dbTextures/Training_3_mc/Layer 3_0_64","frameX":0,"x":68}],"height":256}