{"width":125,"imagePath":"unit8_tex.png","height":102,"name":"unit8","SubTexture":[{"y":1,"frameWidth":20,"x":101,"frameHeight":20,"width":19,"frameY":-1,"height":19,"name":"shadow","frameX":-1},{"y":1,"frameWidth":33,"x":66,"frameHeight":33,"width":33,"frameY":-5,"height":28,"name":"Shape/shape 2622","frameX":0},{"y":59,"frameWidth":35,"x":98,"frameHeight":34,"width":25,"frameY":0,"height":34,"name":"Shape/shape 2628","frameX":-10},{"y":36,"frameWidth":33,"x":1,"frameHeight":33,"width":29,"frameY":-2,"height":31,"name":"Shape/shape 2616","frameX":-4},{"y":1,"frameWidth":33,"x":32,"frameHeight":33,"width":32,"frameY":-4,"height":29,"name":"Shape/shape 2624","frameX":-1},{"y":64,"frameWidth":35,"x":32,"frameHeight":34,"width":28,"frameY":-4,"height":30,"name":"Shape/shape 2634","frameX":-7},{"y":32,"frameWidth":35,"x":32,"frameHeight":34,"width":30,"frameY":-4,"height":30,"name":"Shape/shape 2630","frameX":-5},{"y":59,"frameWidth":33,"x":64,"frameHeight":33,"width":32,"frameY":-5,"height":28,"name":"Shape/shape 2620","frameX":-1},{"y":1,"frameWidth":33,"x":1,"frameHeight":33,"width":29,"frameY":0,"height":33,"name":"Shape/shape 2618","frameX":-4},{"y":31,"frameWidth":35,"x":66,"frameHeight":34,"width":35,"frameY":-8,"height":26,"name":"Shape/shape 2632","frameX":0},{"y":69,"frameWidth":35,"x":1,"frameHeight":34,"width":27,"frameY":-3,"height":31,"name":"Shape/shape 2626","frameX":-8}]}