{"width":124,"height":66,"name":"bullettower5_1","imagePath":"bullettower5_1_tex.png","SubTexture":[{"y":33,"frameY":0,"frameWidth":22,"width":17,"frameX":-2,"frameHeight":31,"height":31,"name":"Shape/shape 10484","x":41},{"y":1,"frameY":-1,"frameWidth":22,"width":18,"frameX":-2,"frameHeight":31,"height":30,"name":"Shape/shape 10470","x":41},{"y":1,"frameY":-1,"frameWidth":22,"width":18,"frameX":-2,"frameHeight":31,"height":30,"name":"Shape/shape 10476","x":101},{"y":33,"frameY":-2,"frameWidth":22,"width":18,"frameX":-2,"frameHeight":31,"height":29,"name":"Shape/shape 10478","x":79},{"y":1,"frameY":0,"frameWidth":22,"width":18,"frameX":-2,"frameHeight":31,"height":31,"name":"Shape/shape 10486","x":21},{"y":1,"frameY":-1,"frameWidth":22,"width":18,"frameX":-2,"frameHeight":31,"height":30,"name":"Shape/shape 10472","x":61},{"y":1,"frameY":-1,"frameWidth":22,"width":18,"frameX":-2,"frameHeight":31,"height":30,"name":"Shape/shape 10480","x":81},{"width":1,"y":1,"height":1,"name":"Shape/shape 10488","x":121},{"y":1,"frameY":0,"frameWidth":22,"width":18,"frameX":-2,"frameHeight":31,"height":31,"name":"Shape/shape 10474","x":1},{"y":33,"frameY":0,"frameWidth":22,"width":17,"frameX":-2,"frameHeight":31,"height":31,"name":"Shape/shape 10482","x":60}]}