{"frameRate":30,"name":"PreVictory_mc","version":"5.5","compatibleVersion":"5.5","armature":[{"type":"Armature","frameRate":30,"name":"PreVictory_mc","aabb":{"x":49.02,"y":-549.89,"width":700,"height":612.95},"bone":[{"name":"root","transform":{"x":399.0226,"y":-299.8872}},{"name":"shadow","parent":"root","transform":{"scX":1.14,"scY":1.2}},{"name":"cont","parent":"root","transform":{"y":180.95}}],"slot":[{"name":"shadow","parent":"shadow"},{"name":"cont","parent":"cont"}],"skin":[{"slot":[{"name":"shadow","display":[{"name":"Shape/shape 5222"},{"name":"sprite 5256"}]},{"name":"cont","display":[{"type":"armature","name":"cont"}]}]}],"animation":[{"duration":13,"fadeInTime":0.3,"name":"PreVictory_mc","bone":[{"name":"cont","translateFrame":[{"duration":4,"tweenEasing":0},{"duration":2,"tweenEasing":0,"y":-180},{"duration":3,"tweenEasing":0,"y":-209.65},{"duration":2,"tweenEasing":0,"y":-177},{"duration":2,"tweenEasing":0,"y":-180.45},{"duration":0,"y":-180.95}],"scaleFrame":[{"duration":4,"tweenEasing":0},{"duration":2,"tweenEasing":0},{"duration":3,"tweenEasing":0,"x":1.11,"y":1.11},{"duration":2,"tweenEasing":0,"x":0.98,"y":0.98},{"duration":2,"tweenEasing":0,"x":1.03},{"duration":0}]}],"slot":[{"name":"cont","colorFrame":[{"duration":4,"tweenEasing":0,"value":{"aM":40}},{"duration":9}]},{"name":"shadow","displayFrame":[{"duration":13},{"duration":0,"value":1}],"colorFrame":[{"duration":6,"tweenEasing":0,"value":{"aM":0}},{"duration":7}]}]}],"defaultActions":[{"gotoAndPlay":"PreVictory_mc"}]},{"type":"Armature","frameRate":30,"name":"cont","aabb":{"x":-272.45,"y":-179,"width":602,"height":364},"bone":[{"name":"root"},{"name":"Masked Layer 2 - 1","parent":"root","transform":{"x":-3,"y":3}},{"name":"Masked Layer 2 - 1_0","parent":"root","transform":{"x":-7.5,"y":3}},{"name":"btnOk","parent":"root","transform":{"y":142}},{"name":"Masked Layer 3 - 1","parent":"root","transform":{"x":-2.25,"y":-130.2}},{"name":"Masked Layer 7 - 1","parent":"root","transform":{"x":15.45,"y":-60.65}},{"name":"Masked Layer 9 - 1","parent":"root","transform":{"x":-112.1,"y":7.85}},{"name":"Masked Layer 11 - 1","parent":"root","transform":{"x":55.55,"y":75.85}},{"name":"Masked Layer 16 - 1","parent":"root","transform":{"x":-6}},{"name":"Layer 18","parent":"root","transform":{"x":11.95,"scX":1.19,"scY":1.19}},{"name":"Layer 19","parent":"root","transform":{"x":-11.95,"scX":1.19,"scY":1.19}}],"slot":[{"name":"Masked Layer 2 - 1","parent":"Masked Layer 2 - 1"},{"name":"Masked Layer 2 - 1_0","parent":"Masked Layer 2 - 1_0"},{"name":"btnOk","parent":"btnOk"},{"name":"Masked Layer 3 - 1","parent":"Masked Layer 3 - 1"},{"name":"Masked Layer 7 - 1","parent":"Masked Layer 7 - 1"},{"name":"Masked Layer 9 - 1","parent":"Masked Layer 9 - 1"},{"name":"Masked Layer 11 - 1","parent":"Masked Layer 11 - 1"},{"name":"Masked Layer 16 - 1","parent":"Masked Layer 16 - 1"},{"name":"Layer 18","parent":"Layer 18"},{"name":"Layer 19","parent":"Layer 19"}],"skin":[{"slot":[{"name":"Masked Layer 2 - 1","display":[{"name":"__dbTextures/cont/Masked Layer 2 - 1_0","transform":{"x":0.5}},{"name":"__dbTextures/cont/Masked Layer 2 - 1_1","transform":{"x":0.45}},{"name":"__dbTextures/cont/Masked Layer 2 - 1_2","transform":{"x":0.35}},{"name":"__dbTextures/cont/Masked Layer 2 - 1_3","transform":{"x":0.25}},{"name":"__dbTextures/cont/Masked Layer 2 - 1_4","transform":{"x":0.2}},{"name":"__dbTextures/cont/Masked Layer 2 - 1_5","transform":{"x":0.1}},{"name":"__dbTextures/cont/Masked Layer 2 - 1_6"},{"name":"Shape/shape 5225","transform":{"x":1,"y":3}}]},{"name":"Masked Layer 16 - 1","display":[{"name":"Shape/shape 12781","transform":{"x":0.05,"y":0.25}}]},{"name":"Masked Layer 11 - 1","display":[{"name":"__dbTextures/cont/Masked Layer 11 - 1_5"},{"name":"__dbTextures/cont/Masked Layer 11 - 1_7"},{"name":"__dbTextures/cont/Masked Layer 11 - 1_15"}]},{"name":"Layer 19","display":[{"name":"Shape/shape 10321","transform":{"x":0.5}}]},{"name":"Masked Layer 3 - 1","display":[{"name":"__dbTextures/cont/Masked Layer 3 - 1_7"},{"name":"__dbTextures/cont/Masked Layer 3 - 1_15"}]},{"name":"btnOk","display":[{"type":"armature","name":"Symbol 10240"}]},{"name":"Layer 18","display":[{"name":"Shape/shape 10319","transform":{"x":0.5,"y":1}}]},{"name":"Masked Layer 7 - 1","display":[{"name":"__dbTextures/cont/Masked Layer 7 - 1_5"},{"name":"__dbTextures/cont/Masked Layer 7 - 1_7"},{"name":"__dbTextures/cont/Masked Layer 7 - 1_15"}]},{"name":"Masked Layer 2 - 1_0","display":[{"name":"__dbTextures/cont/Masked Layer 2 - 1_0"},{"name":"__dbTextures/cont/Masked Layer 2 - 1_0_1"},{"name":"__dbTextures/cont/Masked Layer 2 - 1_0_2"},{"name":"__dbTextures/cont/Masked Layer 2 - 1_0_3"},{"name":"__dbTextures/cont/Masked Layer 2 - 1_0_4"},{"name":"__dbTextures/cont/Masked Layer 2 - 1_0_5"},{"name":"__dbTextures/cont/Masked Layer 2 - 1_0_6"},{"name":"Shape/shape 5225","transform":{"x":1,"y":3}}]},{"name":"Masked Layer 9 - 1","display":[{"name":"__dbTextures/cont/Masked Layer 9 - 1_5"},{"name":"__dbTextures/cont/Masked Layer 9 - 1_7"},{"name":"__dbTextures/cont/Masked Layer 9 - 1_15"}]}]}],"animation":[{"duration":15,"fadeInTime":0.3,"name":"cont","bone":[{"name":"Masked Layer 2 - 1","translateFrame":[{},{"x":24.55},{"x":49.15},{"x":73.75},{"x":98.3},{"x":122.9},{"duration":2,"x":147.5},{"duration":7,"x":3,"y":-3}]},{"name":"Masked Layer 2 - 1_0","translateFrame":[{},{"x":-23.5},{"x":-47},{"x":-70.5},{"x":-94},{"x":-117.5},{"duration":2,"x":-141},{"duration":7,"x":7.5,"y":-3}]},{"name":"Masked Layer 7 - 1","translateFrame":[{"duration":5},{"duration":2},{"duration":8,"x":-5.5,"y":-7.1}]},{"name":"Masked Layer 9 - 1","translateFrame":[{"duration":5},{"duration":2},{"duration":8,"x":-14.9,"y":-17.6}]},{"name":"Masked Layer 11 - 1","translateFrame":[{"duration":5},{"duration":2},{"duration":8,"x":-9,"y":-7}]},{"name":"Layer 18","translateFrame":[{"duration":5,"tweenEasing":0},{"duration":2,"x":222.9},{"duration":8,"x":260.05}]},{"name":"Layer 19","translateFrame":[{"duration":5,"tweenEasing":0},{"duration":2,"x":-222.05},{"duration":8,"x":-259.05}]}],"slot":[{"name":"Masked Layer 11 - 1","displayFrame":[{"duration":5,"value":-1},{"duration":2},{"duration":8,"value":1},{"duration":0,"value":2}]},{"name":"Masked Layer 9 - 1","displayFrame":[{"duration":5,"value":-1},{"duration":2},{"duration":8,"value":1},{"duration":0,"value":2}]},{"name":"Masked Layer 7 - 1","displayFrame":[{"duration":5,"value":-1},{"duration":2},{"duration":8,"value":1},{"duration":0,"value":2}]},{"name":"Masked Layer 3 - 1","displayFrame":[{"duration":7,"value":-1},{"duration":8},{"duration":0,"value":1}]},{"name":"Masked Layer 2 - 1_0","displayFrame":[{},{"value":1},{"value":2},{"value":3},{"value":4},{"value":5},{"duration":2,"value":6},{"duration":7,"value":7}]},{"name":"Masked Layer 2 - 1","displayFrame":[{},{"value":1},{"value":2},{"value":3},{"value":4},{"value":5},{"duration":2,"value":6},{"duration":7,"value":7}]}]}],"defaultActions":[{"gotoAndPlay":"cont"}]},{"type":"Armature","frameRate":30,"name":"Symbol 10240","aabb":{"x":-52.7,"y":-28.85,"width":105,"height":59},"bone":[{"name":"root"},{"name":"Layer 2","parent":"root","transform":{"x":-0.5,"y":0.25}},{"name":"okCase","parent":"root","transform":{"x":-1.7,"y":-1.8,"scX":1.22,"scY":0.67}}],"slot":[{"name":"Layer 2","parent":"Layer 2"},{"name":"okCase","parent":"okCase"}],"skin":[{"slot":[{"name":"okCase","display":[{"name":"Symbol 47"}]},{"name":"Layer 2","display":[{"name":"__dbTextures/Symbol 10240/Layer 2_0","transform":{"x":0.3,"y":0.4}},{"name":"__dbTextures/Symbol 10240/Layer 2_1","transform":{"x":0.3,"y":0.4}},{"name":"__dbTextures/Symbol 10240/Layer 2_2","transform":{"x":0.3,"y":0.4}},{"name":"__dbTextures/Symbol 10240/Layer 2_3","transform":{"x":0.3,"y":0.4}}]}]}],"animation":[{"duration":3,"fadeInTime":0.3,"name":"btnOk","slot":[{"name":"Layer 2","displayFrame":[{},{"value":1},{"value":2},{"duration":0,"value":3}]}]}],"defaultActions":[{"gotoAndPlay":"btnOk"}]}]}