{"SubTexture":[{"width":52,"y":67,"height":55,"name":"Shape/shape 4538","x":1},{"y":67,"frameX":-2,"frameHeight":36,"frameY":-2,"width":32,"frameWidth":36,"height":31,"name":"Shape/shape 4586","x":55},{"y":34,"frameX":-2,"frameHeight":36,"frameY":-2,"width":32,"frameWidth":36,"height":31,"name":"Shape/shape 4572","x":155},{"y":1,"frameX":-2,"frameHeight":36,"frameY":-2,"width":32,"frameWidth":36,"height":31,"name":"Shape/shape 4580","x":189},{"y":223,"frameX":-2,"frameHeight":36,"frameY":-2,"width":32,"frameWidth":36,"height":31,"name":"Shape/shape 4576","x":53},{"y":1,"frameX":-2,"frameHeight":36,"frameY":-2,"width":32,"frameWidth":36,"height":31,"name":"Shape/shape 4570","x":121},{"y":1,"frameX":-2,"frameHeight":36,"frameY":-2,"width":32,"frameWidth":36,"height":31,"name":"Shape/shape 4562","x":155},{"y":1,"frameX":-2,"frameHeight":36,"frameY":-2,"width":32,"frameWidth":36,"height":31,"name":"Shape/shape 4578","x":87},{"y":34,"frameX":-2,"frameHeight":36,"frameY":-2,"width":32,"frameWidth":36,"height":31,"name":"Shape/shape 4560","x":87},{"y":1,"frameX":-2,"frameHeight":36,"frameY":-2,"width":32,"frameWidth":36,"height":31,"name":"Shape/shape 4544","x":223},{"y":190,"frameX":-2,"frameHeight":36,"frameY":-2,"width":32,"frameWidth":36,"height":31,"name":"Shape/shape 4588","x":53},{"y":34,"frameX":-2,"frameHeight":36,"frameY":-2,"width":32,"frameWidth":36,"height":31,"name":"Shape/shape 4564","x":223},{"y":100,"frameX":-2,"frameHeight":36,"frameY":-2,"width":32,"frameWidth":36,"height":31,"name":"Shape/shape 4550","x":189},{"y":199,"frameX":-2,"frameHeight":36,"frameY":-2,"width":32,"frameWidth":36,"height":31,"name":"Shape/shape 4558","x":87},{"y":100,"frameX":-2,"frameHeight":36,"frameY":-2,"width":32,"frameWidth":36,"height":31,"name":"Shape/shape 4540","x":121},{"y":124,"frameX":-2,"frameHeight":36,"frameY":-2,"width":32,"frameWidth":36,"height":31,"name":"Shape/shape 4568","x":53},{"y":67,"frameX":-2,"frameHeight":36,"frameY":-2,"width":32,"frameWidth":36,"height":31,"name":"Shape/shape 4548","x":123},{"y":166,"frameX":-2,"frameHeight":36,"frameY":-2,"width":32,"frameWidth":36,"height":31,"name":"Shape/shape 4556","x":87},{"y":34,"frameX":-2,"frameHeight":36,"frameY":-2,"width":32,"frameWidth":36,"height":31,"name":"Shape/shape 4542","x":121},{"y":34,"frameX":-2,"frameHeight":36,"frameY":-2,"width":32,"frameWidth":36,"height":31,"name":"Shape/shape 4554","x":189},{"y":133,"frameX":-2,"frameHeight":36,"frameY":-2,"width":32,"frameWidth":36,"height":31,"name":"Shape/shape 4574","x":87},{"y":67,"frameX":-2,"frameHeight":36,"frameY":-2,"width":32,"frameWidth":36,"height":31,"name":"Shape/shape 4546","x":89},{"y":100,"frameX":-2,"frameHeight":36,"frameY":-2,"width":32,"frameWidth":36,"height":31,"name":"Shape/shape 4566","x":155},{"y":100,"frameX":-2,"frameHeight":36,"frameY":-2,"width":32,"frameWidth":36,"height":31,"name":"Shape/shape 4582","x":87},{"y":67,"frameX":-2,"frameHeight":36,"frameY":-2,"width":32,"frameWidth":36,"height":31,"name":"Shape/shape 4584","x":157},{"y":157,"frameX":-2,"frameHeight":36,"frameY":-2,"width":32,"frameWidth":36,"height":31,"name":"Shape/shape 4552","x":53},{"y":1,"frameX":-1,"frameHeight":66,"frameY":-2,"width":60,"frameWidth":62,"height":64,"name":"selectTower","x":1},{"width":50,"y":176,"height":50,"name":"case","x":1},{"width":50,"y":124,"height":50,"name":"sphere","x":1}],"width":256,"imagePath":"Tower3_mc_tex.png","name":"Tower3_mc","height":256}