{"width":256,"imagePath":"CastIce_mc_tex.png","height":512,"name":"CastIce_mc","SubTexture":[{"width":108,"y":103,"height":100,"name":"Shape/shape 7481","x":111},{"y":396,"frameWidth":108,"x":168,"frameHeight":100,"width":66,"frameY":-19,"height":56,"name":"Shape/shape 7471","frameX":-21},{"width":108,"y":103,"height":100,"name":"Shape/shape 7487","x":1},{"width":108,"y":1,"height":100,"name":"Shape/shape 7489","x":111},{"y":396,"frameWidth":108,"x":1,"frameHeight":100,"width":85,"frameY":-13,"height":75,"name":"Shape/shape 7475","frameX":-10},{"y":205,"frameWidth":108,"x":111,"frameHeight":100,"width":108,"frameY":0,"height":99,"name":"Shape/shape 7479","frameX":0},{"y":205,"frameWidth":108,"x":1,"frameHeight":100,"width":108,"frameY":-1,"height":99,"name":"Shape/shape 7483","frameX":0},{"width":108,"y":1,"height":100,"name":"Shape/shape 7485","x":1},{"y":396,"frameWidth":108,"x":88,"frameHeight":100,"width":78,"frameY":-15,"height":67,"name":"Shape/shape 7473","frameX":-15},{"y":306,"frameWidth":108,"x":1,"frameHeight":100,"width":100,"frameY":-5,"height":88,"name":"Shape/shape 7477","frameX":-4}]}