{"width":256,"SubTexture":[{"frameWidth":65,"y":153,"frameHeight":47,"width":65,"frameX":0,"height":12,"name":"Shape/shape 2316","frameY":-35,"x":60},{"frameWidth":65,"y":129,"frameHeight":47,"width":57,"frameX":-1,"height":42,"name":"Shape/shape 2334","frameY":-5,"x":1},{"frameWidth":65,"y":87,"frameHeight":47,"width":65,"frameX":0,"height":40,"name":"Shape/shape 2331","frameY":-7,"x":1},{"frameWidth":65,"y":229,"frameHeight":47,"width":65,"frameX":0,"height":9,"name":"Shape/shape 2314","frameY":-38,"x":38},{"frameWidth":65,"y":1,"frameHeight":47,"width":65,"frameX":0,"height":41,"name":"Shape/shape 2329","frameY":-6,"x":133},{"frameWidth":65,"y":240,"frameHeight":47,"width":65,"frameX":0,"height":6,"name":"Shape/shape 2312","frameY":-41,"x":38},{"frameWidth":65,"y":167,"frameHeight":47,"width":65,"frameX":0,"height":4,"name":"Shape/shape 2310","frameY":-43,"x":60},{"frameWidth":65,"y":1,"frameHeight":47,"width":65,"frameX":0,"height":42,"name":"Shape/shape 2328","frameY":-5,"x":66},{"frameWidth":65,"y":44,"frameHeight":47,"width":65,"frameX":0,"height":41,"name":"Shape/shape 2326","frameY":-6,"x":133},{"frameWidth":65,"y":129,"frameHeight":47,"width":2,"frameX":0,"height":2,"name":"Shape/shape 2308","frameY":-45,"x":60},{"frameWidth":65,"y":45,"frameHeight":47,"width":65,"frameX":0,"height":40,"name":"Shape/shape 2324","frameY":-7,"x":66},{"frameWidth":65,"y":1,"frameHeight":47,"width":63,"frameX":-2,"height":45,"name":"Shape/shape 2338","frameY":0,"x":1},{"frameWidth":65,"y":173,"frameHeight":47,"width":65,"frameX":0,"height":28,"name":"Shape/shape 2322","frameY":-19,"x":1},{"frameWidth":65,"y":87,"frameHeight":47,"width":59,"frameX":-2,"height":44,"name":"Shape/shape 2336","frameY":-2,"x":68},{"frameWidth":65,"y":133,"frameHeight":47,"width":65,"frameX":0,"height":18,"name":"Shape/shape 2318","frameY":-29,"x":60},{"width":11,"y":75,"height":8,"name":"__dbTextures/Training_4_mc/Layer 2_5","x":1},{"width":36,"y":48,"height":25,"name":"__dbTextures/Training_4_mc/Layer 2_9","x":1},{"frameWidth":35,"y":230,"frameHeight":25,"width":35,"frameX":0,"height":24,"name":"__dbTextures/Training_4_mc/Layer 2_12","frameY":0,"x":1},{"width":35,"y":203,"height":25,"name":"__dbTextures/Training_4_mc/Layer 2_22","x":1},{"frameWidth":35,"y":203,"frameHeight":25,"width":35,"frameX":0,"height":24,"name":"__dbTextures/Training_4_mc/Layer 2_11","frameY":0,"x":38}],"height":256,"name":"Training_4_mc","imagePath":"Training_4_mc_tex.png"}