{"imagePath":"BuildTowerMenu_mc_tex.png","width":256,"SubTexture":[{"y":101,"frameX":-1,"frameY":-2,"width":23,"frameWidth":26,"height":26,"name":"Shape/shape 12135","frameHeight":30,"x":132},{"y":56,"frameX":0,"frameY":0,"width":40,"frameWidth":41,"height":53,"name":"Shape/shape 12147","frameHeight":54,"x":90},{"y":51,"frameX":-1,"frameY":-2,"width":32,"frameWidth":35,"height":41,"name":"Shape/shape 12125","frameHeight":44,"x":171},{"y":51,"frameX":0,"frameY":-2,"width":37,"frameWidth":39,"height":48,"name":"Shape/shape 12141","frameHeight":51,"x":132},{"y":58,"frameX":-1,"frameY":0,"width":43,"frameWidth":45,"height":55,"name":"Shape/shape 12143","frameHeight":57,"x":1},{"y":93,"frameX":-1,"frameY":-2,"width":26,"frameWidth":29,"height":34,"name":"Shape/shape 12137","frameHeight":38,"x":205},{"y":1,"frameX":-1,"frameY":0,"width":43,"frameWidth":46,"height":55,"name":"Shape/shape 12129","frameHeight":58,"x":1},{"y":51,"frameX":-1,"frameY":-2,"width":31,"frameWidth":33,"height":40,"name":"Shape/shape 12139","frameHeight":45,"x":205},{"y":94,"frameX":-2,"frameY":-3,"width":26,"frameWidth":31,"height":33,"name":"Shape/shape 12123","frameHeight":38,"x":171},{"y":57,"frameX":0,"frameY":-1,"width":42,"frameWidth":43,"height":53,"name":"Shape/shape 12145","frameHeight":57,"x":46},{"y":1,"frameX":0,"frameY":-2,"width":38,"frameWidth":40,"height":48,"name":"Shape/shape 12127","frameHeight":52,"x":132},{"y":1,"frameX":0,"frameY":0,"width":40,"frameWidth":41,"height":53,"name":"Shape/shape 12133","frameHeight":54,"x":90},{"y":93,"frameX":-1,"frameY":-1,"width":22,"frameWidth":25,"height":26,"name":"Shape/shape 12119","frameHeight":29,"x":233},{"y":1,"frameX":0,"frameY":-1,"width":42,"frameWidth":43,"height":54,"name":"Shape/shape 12131","frameHeight":58,"x":46},{"y":101,"frameX":-17,"frameY":-7,"width":12,"frameWidth":41,"height":9,"name":"cont","frameHeight":54,"x":157}],"height":128,"name":"BuildTowerMenu_mc"}