{"frameRate":30,"name":"RoadUnitIce_mc","version":"5.5","compatibleVersion":"5.5","armature":[{"type":"Armature","frameRate":30,"name":"RoadUnitIce_mc","aabb":{"x":-22,"y":-45,"width":49,"height":56},"bone":[{"name":"root"},{"name":"Layer 1","parent":"root"},{"name":"Layer 2","parent":"root"}],"slot":[{"name":"Layer 1","parent":"Layer 1"},{"name":"Layer 2","parent":"Layer 2"}],"skin":[{"slot":[{"name":"Layer 2","display":[{"name":"Shape/shape 11599","transform":{"x":2.5,"y":-17}},{"name":"Shape/shape 11602","transform":{"x":2.5,"y":-17}},{"name":"Shape/shape 11605","transform":{"x":2.5,"y":-17}},{"name":"Shape/shape 11608","transform":{"x":2.5,"y":-17}},{"name":"Shape/shape 11611","transform":{"x":2.5,"y":-17}},{"name":"Shape/shape 11614","transform":{"x":2.5,"y":-17}}]},{"name":"Layer 1","display":[{"name":"Shape/shape 11616","transform":{"x":2.5,"y":-17}},{"name":"Shape/shape 11618","transform":{"x":2.5,"y":-17}},{"name":"Shape/shape 11620","transform":{"x":2.5,"y":-17}},{"name":"Shape/shape 11622","transform":{"x":2.5,"y":-17}},{"name":"Shape/shape 11624","transform":{"x":2.5,"y":-17}}]}]}],"animation":[{"duration":22,"fadeInTime":0.3,"name":"RoadUnitIce_mc","frame":[{"duration":22},{"duration":0}],"slot":[{"name":"Layer 2","displayFrame":[{"duration":2},{"duration":2,"value":1},{"duration":2,"value":2},{"duration":2,"value":3},{"duration":2,"value":4},{"duration":2,"value":5},{"duration":10,"value":-1}]},{"name":"Layer 1","displayFrame":[{"duration":12,"value":-1},{"duration":2},{"duration":2,"value":1},{"duration":2,"value":2},{"duration":2,"value":3},{"duration":2,"value":4}]}]}],"defaultActions":[{"gotoAndPlay":"RoadUnitIce_mc"}]}]}