{"width":1024,"imagePath":"OpenLevel_mc_tex.png","height":2048,"name":"OpenLevel_mc","SubTexture":[{"width":700,"y":1,"height":500,"name":"Symbol 1600","x":1},{"frameY":-1,"y":503,"frameWidth":608,"frameX":0,"frameHeight":449,"width":608,"height":448,"name":"__dbTextures/Symbol 6089/Layer 14_0","x":1},{"width":44,"y":1534,"height":21,"name":"位图 13","x":818},{"frameY":-1,"y":649,"frameWidth":56,"frameX":0,"frameHeight":29,"width":56,"height":28,"name":"位图 16","x":849},{"frameY":-1,"y":953,"frameWidth":36,"frameX":0,"frameHeight":16,"width":36,"height":15,"name":"位图 22","x":954},{"frameY":-1,"y":1393,"frameWidth":13,"frameX":-3,"frameHeight":14,"width":10,"height":13,"name":"位图 14","x":960},{"frameY":-1,"y":1557,"frameWidth":44,"frameX":-3,"frameHeight":19,"width":41,"height":18,"name":"位图 23","x":810},{"frameY":-2,"y":953,"frameWidth":58,"frameX":-3,"frameHeight":29,"width":55,"height":27,"name":"位图 15","x":538},{"width":44,"y":1350,"height":29,"name":"位图 24","x":862},{"frameY":0,"y":827,"frameWidth":15,"frameX":-3,"frameHeight":34,"width":12,"height":34,"name":"位图 18","x":1006},{"frameY":-1,"y":953,"frameWidth":55,"frameX":0,"frameHeight":29,"width":55,"height":28,"name":"位图 25","x":425},{"frameY":-2,"y":972,"frameWidth":172,"frameX":-3,"frameHeight":36,"width":169,"height":34,"name":"位图 17","x":849},{"width":1,"y":1431,"height":1,"name":"text","x":919},{"frameY":-1,"y":953,"frameWidth":54,"frameX":0,"frameHeight":29,"width":54,"height":28,"name":"位图 26","x":482},{"frameY":-1,"y":279,"frameWidth":17,"frameX":-2,"frameHeight":58,"width":15,"height":57,"name":"位图 19","x":997},{"width":44,"y":1433,"height":29,"name":"位图 27","x":671},{"frameY":0,"y":729,"frameWidth":20,"frameX":-3,"frameHeight":31,"width":17,"height":31,"name":"位图 28","x":1006},{"width":34,"y":1505,"height":29,"name":"位图 20","x":782},{"frameY":-2,"y":583,"frameWidth":31,"frameX":-3,"frameHeight":20,"width":28,"height":18,"name":"位图 21","x":995},{"frameY":0,"y":1498,"frameWidth":36,"frameX":0,"frameHeight":29,"width":36,"height":28,"name":"Symbol 5720","x":642},{"frameY":0,"y":1558,"frameWidth":36,"frameX":0,"frameHeight":29,"width":36,"height":28,"name":"Symbol 5714","x":642},{"frameY":0,"y":1495,"frameWidth":36,"frameX":0,"frameHeight":29,"width":36,"height":28,"name":"Symbol 5723","x":744},{"frameY":0,"y":1528,"frameWidth":36,"frameX":0,"frameHeight":29,"width":36,"height":28,"name":"Symbol 5717","x":642},{"frameY":0,"y":1351,"frameWidth":29,"frameX":0,"frameHeight":24,"width":20,"height":14,"name":"元件 3","x":711},{"width":30,"y":1605,"height":13,"name":"元件 5","x":932},{"frameY":0,"y":1449,"frameWidth":29,"frameX":0,"frameHeight":24,"width":20,"height":12,"name":"元件 1","x":642},{"frameY":0,"y":416,"frameWidth":31,"frameX":0,"frameHeight":24,"width":21,"height":15,"name":"元件 6","x":999},{"width":50,"y":782,"height":50,"name":"Symbol 47","x":912},{"width":210,"y":1105,"height":150,"name":"__dbTextures/Symbol 5757/Layer 2_3","x":1},{"width":210,"y":833,"height":150,"name":"__dbTextures/Symbol 5757/Layer 2_7","x":611},{"width":210,"y":1257,"height":150,"name":"__dbTextures/Symbol 5757/Layer 2_14","x":213},{"width":210,"y":1289,"height":150,"name":"__dbTextures/Symbol 5757/Layer 2_13","x":425},{"width":210,"y":1257,"height":150,"name":"__dbTextures/Symbol 5757/Layer 2_15","x":1},{"width":210,"y":953,"height":150,"name":"__dbTextures/Symbol 5757/Layer 2_6","x":213},{"width":210,"y":1137,"height":150,"name":"__dbTextures/Symbol 5757/Layer 2_10","x":425},{"width":210,"y":681,"height":150,"name":"__dbTextures/Symbol 5757/Layer 2_11","x":611},{"width":210,"y":1105,"height":150,"name":"__dbTextures/Symbol 5757/Layer 2_2","x":213},{"width":210,"y":985,"height":150,"name":"__dbTextures/Symbol 5757/Layer 2_4","x":425},{"width":210,"y":985,"height":150,"name":"__dbTextures/Symbol 5757/Layer 2_1","x":637},{"width":210,"y":953,"height":150,"name":"__dbTextures/Symbol 5757/Layer 2_5","x":1},{"width":210,"y":1,"height":150,"name":"__dbTextures/Symbol 5757/Layer 2_9","x":703},{"width":210,"y":153,"height":150,"name":"__dbTextures/Symbol 5757/Layer 2_12","x":703},{"width":210,"y":1137,"height":150,"name":"__dbTextures/Symbol 5757/Layer 2_0","x":637},{"width":210,"y":305,"height":150,"name":"__dbTextures/Symbol 5757/Layer 2_8","x":703},{"frameY":0,"y":503,"frameWidth":237,"frameX":0,"frameHeight":176,"width":236,"height":176,"name":"Symbol 5728","x":611},{"frameY":-2,"y":457,"frameWidth":94,"frameX":0,"frameHeight":101,"width":94,"height":93,"name":"Symbol 5759","x":849},{"frameY":-2,"y":681,"frameWidth":94,"frameX":0,"frameHeight":101,"width":94,"height":99,"name":"Symbol 5775","x":823},{"frameY":-2,"y":782,"frameWidth":94,"frameX":-2,"frameHeight":101,"width":87,"height":93,"name":"Symbol 5773","x":823},{"frameY":-1,"y":552,"frameWidth":50,"frameX":0,"frameHeight":50,"width":50,"height":49,"name":"Symbol 5770","x":943},{"frameY":-2,"y":877,"frameWidth":94,"frameX":-2,"frameHeight":101,"width":87,"height":93,"name":"Symbol 5780","x":823},{"frameY":0,"y":552,"frameWidth":94,"frameX":-2,"frameHeight":101,"width":92,"height":95,"name":"Symbol 5778","x":849},{"frameY":0,"y":1289,"frameWidth":39,"frameX":0,"frameHeight":37,"width":39,"height":36,"name":"Symbol 5782","x":760},{"frameY":0,"y":1274,"frameWidth":39,"frameX":0,"frameHeight":37,"width":39,"height":36,"name":"__dbTextures/Symbol 5784/Layer 1_1","x":890},{"width":27,"y":1367,"height":20,"name":"Symbol 5786","x":745},{"width":26,"y":945,"height":20,"name":"Symbol 5785","x":996},{"frameY":0,"y":1353,"frameWidth":25,"frameX":-7,"frameHeight":31,"width":18,"height":31,"name":"位图 11","x":810},{"frameY":-1,"y":1327,"frameWidth":61,"frameX":0,"frameHeight":23,"width":61,"height":22,"name":"位图 8","x":674},{"frameY":-6,"y":1289,"frameWidth":30,"frameX":0,"frameHeight":22,"width":4,"height":16,"name":"位图 12","x":842},{"width":54,"y":1327,"height":24,"name":"位图 9","x":774},{"frameY":0,"y":791,"frameWidth":15,"frameX":-2,"frameHeight":34,"width":13,"height":34,"name":"位图 10","x":1006},{"frameY":-6,"y":1561,"frameWidth":160,"frameX":-7,"frameHeight":25,"width":38,"height":19,"name":"位图 2","x":853},{"frameY":-1,"y":517,"frameWidth":54,"frameX":0,"frameHeight":27,"width":54,"height":26,"name":"位图 6","x":945},{"frameY":-3,"y":1619,"frameWidth":24,"frameX":-3,"frameHeight":27,"width":21,"height":17,"name":"位图 3","x":964},{"frameY":-6,"y":1568,"frameWidth":48,"frameX":-6,"frameHeight":27,"width":39,"height":21,"name":"位图 7","x":744},{"frameY":-2,"y":1606,"frameWidth":26,"frameX":-6,"frameHeight":23,"width":20,"height":21,"name":"位图 4","x":908},{"frameY":-3,"y":1586,"frameWidth":27,"frameX":-3,"frameHeight":27,"width":24,"height":17,"name":"位图 1","x":932},{"frameY":0,"y":1582,"frameWidth":25,"frameX":-3,"frameHeight":27,"width":22,"height":20,"name":"位图 5","x":860},{"width":275,"y":1409,"height":60,"name":"__dbTextures/Symbol 6088/Layer 12_0","x":1},{"frameY":-1,"y":457,"frameWidth":85,"frameX":-5,"frameHeight":55,"width":69,"height":39,"name":"Symbol 5834","x":703},{"width":38,"y":283,"height":38,"name":"Symbol 6085","x":915},{"width":38,"y":243,"height":38,"name":"Symbol 6087","x":915},{"width":38,"y":323,"height":38,"name":"Symbol 6083","x":915},{"frameY":-2,"y":1540,"frameWidth":45,"frameX":-2,"frameHeight":26,"width":38,"height":19,"name":"__dbTextures/Symbol 5768/Layer 1_6","x":905},{"width":45,"y":1353,"height":26,"name":"__dbTextures/Symbol 5768/Layer 1_9","x":975},{"frameY":-2,"y":1540,"frameWidth":45,"frameX":-1,"frameHeight":26,"width":39,"height":19,"name":"__dbTextures/Symbol 5768/Layer 1_12","x":864},{"frameY":0,"y":1444,"frameWidth":45,"frameX":0,"frameHeight":26,"width":40,"height":26,"name":"__dbTextures/Symbol 5768/Layer 1_15","x":952},{"frameY":-1,"y":1468,"frameWidth":45,"frameX":0,"frameHeight":26,"width":45,"height":25,"name":"__dbTextures/Symbol 5768/Layer 1_0","x":752},{"width":45,"y":1381,"height":26,"name":"__dbTextures/Symbol 5768/Layer 1_3","x":975},{"frameY":-8,"y":1,"frameWidth":30,"frameX":-3,"frameHeight":48,"width":20,"height":35,"name":"__dbTextures/Symbol 5822/Layer 1_10","x":915},{"frameY":-15,"y":762,"frameWidth":30,"frameX":-3,"frameHeight":48,"width":17,"height":27,"name":"__dbTextures/Symbol 5822/Layer 1_0","x":1006},{"frameY":-6,"y":377,"frameWidth":30,"frameX":-3,"frameHeight":48,"width":20,"height":37,"name":"__dbTextures/Symbol 5822/Layer 1_12","x":999},{"frameY":-15,"y":157,"frameWidth":30,"frameX":-3,"frameHeight":48,"width":19,"height":27,"name":"__dbTextures/Symbol 5822/Layer 1_26","x":915},{"frameY":-14,"y":98,"frameWidth":30,"frameX":-2,"frameHeight":48,"width":19,"height":28,"name":"__dbTextures/Symbol 5822/Layer 1_2","x":915},{"frameY":-5,"y":338,"frameWidth":30,"frameX":-2,"frameHeight":48,"width":21,"height":37,"name":"__dbTextures/Symbol 5822/Layer 1_14","x":997},{"frameY":0,"y":1350,"frameWidth":30,"frameX":0,"frameHeight":48,"width":30,"height":43,"name":"__dbTextures/Symbol 5822/Layer 1_16","x":830},{"frameY":-12,"y":1435,"frameWidth":30,"frameX":-2,"frameHeight":48,"width":21,"height":31,"name":"__dbTextures/Symbol 5822/Layer 1_8","x":752},{"frameY":-3,"y":687,"frameWidth":30,"frameX":-2,"frameHeight":48,"width":20,"height":40,"name":"__dbTextures/Symbol 5822/Layer 1_18","x":1003},{"frameY":-3,"y":1312,"frameWidth":30,"frameX":0,"frameHeight":48,"width":21,"height":39,"name":"__dbTextures/Symbol 5822/Layer 1_20","x":1002},{"frameY":-14,"y":1409,"frameWidth":30,"frameX":-3,"frameHeight":48,"width":19,"height":28,"name":"__dbTextures/Symbol 5822/Layer 1_4","x":404},{"frameY":-14,"y":68,"frameWidth":30,"frameX":-3,"frameHeight":48,"width":20,"height":28,"name":"__dbTextures/Symbol 5822/Layer 1_6","x":915},{"frameY":-3,"y":1528,"frameWidth":30,"frameX":-3,"frameHeight":48,"width":19,"height":39,"name":"__dbTextures/Symbol 5822/Layer 1_22","x":680},{"frameY":-15,"y":128,"frameWidth":30,"frameX":-3,"frameHeight":48,"width":19,"height":27,"name":"__dbTextures/Symbol 5822/Layer 1_24","x":915},{"frameY":-4,"y":1464,"frameWidth":44,"frameX":-4,"frameHeight":44,"width":32,"height":32,"name":"__dbTextures/Symbol 5905/Layer 1_18","x":676},{"frameY":-4,"y":1540,"frameWidth":44,"frameX":-4,"frameHeight":44,"width":32,"height":32,"name":"__dbTextures/Symbol 5905/Layer 1_33","x":981},{"frameY":-4,"y":1441,"frameWidth":44,"frameX":-4,"frameHeight":44,"width":32,"height":32,"name":"__dbTextures/Symbol 5905/Layer 1_26","x":438},{"frameY":-4,"y":1585,"frameWidth":44,"frameX":-4,"frameHeight":44,"width":32,"height":32,"name":"__dbTextures/Symbol 5905/Layer 1_28","x":608},{"frameY":0,"y":1,"frameWidth":44,"frameX":0,"frameHeight":44,"width":44,"height":36,"name":"__dbTextures/Symbol 5905/Layer 1_8","x":945},{"frameY":-4,"y":1500,"frameWidth":44,"frameX":-4,"frameHeight":44,"width":32,"height":32,"name":"__dbTextures/Symbol 5905/Layer 1_0","x":845},{"frameY":-4,"y":1409,"frameWidth":44,"frameX":-4,"frameHeight":44,"width":32,"height":33,"name":"__dbTextures/Symbol 5905/Layer 1_29","x":960},{"frameY":-4,"y":1506,"frameWidth":44,"frameX":-4,"frameHeight":44,"width":32,"height":32,"name":"__dbTextures/Symbol 5905/Layer 1_21","x":947},{"frameY":-3,"y":1,"frameWidth":44,"frameX":-4,"frameHeight":44,"width":32,"height":34,"name":"__dbTextures/Symbol 5905/Layer 1_31","x":991},{"frameY":-4,"y":1473,"frameWidth":44,"frameX":-4,"frameHeight":44,"width":32,"height":32,"name":"__dbTextures/Symbol 5905/Layer 1_22","x":710},{"frameY":-4,"y":1464,"frameWidth":44,"frameX":-4,"frameHeight":44,"width":32,"height":32,"name":"__dbTextures/Symbol 5905/Layer 1_14","x":642},{"frameY":-4,"y":1483,"frameWidth":44,"frameX":-4,"frameHeight":44,"width":32,"height":32,"name":"__dbTextures/Symbol 5905/Layer 1_11","x":608},{"frameY":-4,"y":1393,"frameWidth":44,"frameX":-4,"frameHeight":44,"width":40,"height":32,"name":"__dbTextures/Symbol 5905/Layer 1_15","x":779},{"frameY":0,"y":1435,"frameWidth":44,"frameX":-4,"frameHeight":44,"width":33,"height":36,"name":"__dbTextures/Symbol 5905/Layer 1_23","x":717},{"frameY":-4,"y":1441,"frameWidth":44,"frameX":-4,"frameHeight":44,"width":32,"height":32,"name":"__dbTextures/Symbol 5905/Layer 1_1","x":540},{"frameY":-4,"y":1449,"frameWidth":44,"frameX":-4,"frameHeight":44,"width":32,"height":32,"name":"__dbTextures/Symbol 5905/Layer 1_34","x":608},{"frameY":-4,"y":1506,"frameWidth":44,"frameX":-4,"frameHeight":44,"width":32,"height":32,"name":"__dbTextures/Symbol 5905/Layer 1_32","x":879},{"frameY":-4,"y":1507,"frameWidth":44,"frameX":-4,"frameHeight":44,"width":32,"height":32,"name":"__dbTextures/Symbol 5905/Layer 1_24","x":710},{"frameY":-4,"y":1506,"frameWidth":44,"frameX":-4,"frameHeight":44,"width":32,"height":32,"name":"__dbTextures/Symbol 5905/Layer 1_16","x":981},{"frameY":-4,"y":1447,"frameWidth":44,"frameX":-4,"frameHeight":44,"width":32,"height":32,"name":"__dbTextures/Symbol 5905/Layer 1_9","x":346},{"frameY":-4,"y":1541,"frameWidth":44,"frameX":-4,"frameHeight":44,"width":32,"height":32,"name":"__dbTextures/Symbol 5905/Layer 1_17","x":710},{"frameY":-4,"y":1441,"frameWidth":44,"frameX":-4,"frameHeight":44,"width":32,"height":32,"name":"__dbTextures/Symbol 5905/Layer 1_27","x":506},{"frameY":-4,"y":1441,"frameWidth":44,"frameX":-4,"frameHeight":44,"width":32,"height":32,"name":"__dbTextures/Symbol 5905/Layer 1_19","x":574},{"frameY":-4,"y":1447,"frameWidth":44,"frameX":-4,"frameHeight":44,"width":32,"height":32,"name":"__dbTextures/Symbol 5905/Layer 1_20","x":312},{"frameY":-4,"y":1472,"frameWidth":44,"frameX":-4,"frameHeight":44,"width":32,"height":32,"name":"__dbTextures/Symbol 5905/Layer 1_7","x":919},{"frameY":-4,"y":1447,"frameWidth":44,"frameX":-4,"frameHeight":44,"width":32,"height":32,"name":"__dbTextures/Symbol 5905/Layer 1_6","x":278},{"frameY":-4,"y":1441,"frameWidth":44,"frameX":-4,"frameHeight":44,"width":32,"height":32,"name":"__dbTextures/Symbol 5905/Layer 1_4","x":404},{"frameY":-4,"y":1551,"frameWidth":44,"frameX":-4,"frameHeight":44,"width":32,"height":32,"name":"__dbTextures/Symbol 5905/Layer 1_10","x":608},{"frameY":-4,"y":1472,"frameWidth":44,"frameX":-4,"frameHeight":44,"width":32,"height":32,"name":"__dbTextures/Symbol 5905/Layer 1_5","x":987},{"frameY":-4,"y":1517,"frameWidth":44,"frameX":-4,"frameHeight":44,"width":32,"height":32,"name":"__dbTextures/Symbol 5905/Layer 1_2","x":608},{"frameY":-4,"y":1506,"frameWidth":44,"frameX":-4,"frameHeight":44,"width":32,"height":32,"name":"__dbTextures/Symbol 5905/Layer 1_12","x":913},{"frameY":-4,"y":1441,"frameWidth":44,"frameX":-4,"frameHeight":44,"width":32,"height":32,"name":"__dbTextures/Symbol 5905/Layer 1_25","x":472},{"frameY":-3,"y":206,"frameWidth":44,"frameX":-4,"frameHeight":44,"width":32,"height":34,"name":"__dbTextures/Symbol 5905/Layer 1_30","x":987},{"frameY":-4,"y":457,"frameWidth":44,"frameX":0,"frameHeight":44,"width":44,"height":40,"name":"__dbTextures/Symbol 5905/Layer 1_60","x":774},{"frameY":-4,"y":1472,"frameWidth":44,"frameX":-4,"frameHeight":44,"width":32,"height":32,"name":"__dbTextures/Symbol 5905/Layer 1_13","x":881},{"frameY":-4,"y":1472,"frameWidth":44,"frameX":-4,"frameHeight":44,"width":32,"height":32,"name":"__dbTextures/Symbol 5905/Layer 1_3","x":953},{"frameY":-2,"y":1351,"frameWidth":35,"frameX":0,"frameHeight":40,"width":35,"height":38,"name":"__dbTextures/Symbol 5936/Layer 2_16","x":674},{"frameY":-3,"y":1368,"frameWidth":35,"frameX":0,"frameHeight":40,"width":35,"height":37,"name":"__dbTextures/Symbol 5936/Layer 2_18","x":637},{"frameY":-2,"y":1422,"frameWidth":35,"frameX":0,"frameHeight":40,"width":31,"height":38,"name":"__dbTextures/Symbol 5936/Layer 2_0","x":855},{"frameY":-2,"y":1395,"frameWidth":35,"frameX":0,"frameHeight":40,"width":32,"height":38,"name":"__dbTextures/Symbol 5936/Layer 2_20","x":821},{"frameY":-2,"y":1327,"frameWidth":35,"frameX":0,"frameHeight":40,"width":35,"height":38,"name":"__dbTextures/Symbol 5936/Layer 2_2","x":737},{"width":35,"y":123,"height":40,"name":"__dbTextures/Symbol 5936/Layer 2_22","x":987},{"frameY":-2,"y":1353,"frameWidth":35,"frameX":0,"frameHeight":40,"width":31,"height":38,"name":"__dbTextures/Symbol 5936/Layer 2_4","x":942},{"frameY":-1,"y":1312,"frameWidth":35,"frameX":0,"frameHeight":40,"width":35,"height":39,"name":"__dbTextures/Symbol 5936/Layer 2_24","x":965},{"frameY":-1,"y":1327,"frameWidth":35,"frameX":0,"frameHeight":40,"width":35,"height":39,"name":"__dbTextures/Symbol 5936/Layer 2_6","x":637},{"frameY":-1,"y":1350,"frameWidth":35,"frameX":0,"frameHeight":40,"width":32,"height":39,"name":"__dbTextures/Symbol 5936/Layer 2_26","x":908},{"frameY":0,"y":1407,"frameWidth":35,"frameX":0,"frameHeight":40,"width":32,"height":40,"name":"__dbTextures/Symbol 5936/Layer 2_8","x":637},{"width":35,"y":475,"height":40,"name":"__dbTextures/Symbol 5936/Layer 2_28","x":987},{"frameY":0,"y":1393,"frameWidth":35,"frameX":0,"frameHeight":40,"width":32,"height":40,"name":"__dbTextures/Symbol 5936/Layer 2_10","x":745},{"frameY":-1,"y":1427,"frameWidth":35,"frameX":0,"frameHeight":40,"width":31,"height":39,"name":"__dbTextures/Symbol 5936/Layer 2_30","x":779},{"frameY":0,"y":1391,"frameWidth":35,"frameX":0,"frameHeight":40,"width":32,"height":40,"name":"__dbTextures/Symbol 5936/Layer 2_12","x":674},{"width":35,"y":81,"height":40,"name":"__dbTextures/Symbol 5936/Layer 2_14","x":987},{"width":50,"y":649,"height":50,"name":"Symbol 4085","x":919},{"frameY":0,"y":1289,"frameWidth":40,"frameX":0,"frameHeight":36,"width":39,"height":36,"name":"__dbTextures/Symbol 6012/Layer 2_14","x":678},{"width":40,"y":1084,"height":36,"name":"__dbTextures/Symbol 6012/Layer 2_24","x":849},{"width":40,"y":1409,"height":36,"name":"__dbTextures/Symbol 6012/Layer 2_33","x":320},{"width":40,"y":1008,"height":36,"name":"__dbTextures/Symbol 6012/Layer 2_38","x":975},{"frameY":0,"y":1274,"frameWidth":40,"frameX":0,"frameHeight":36,"width":39,"height":36,"name":"__dbTextures/Symbol 6012/Layer 2_16","x":931},{"width":40,"y":281,"height":36,"name":"__dbTextures/Symbol 6012/Layer 2_22","x":955},{"frameY":0,"y":1236,"frameWidth":40,"frameX":0,"frameHeight":36,"width":39,"height":36,"name":"__dbTextures/Symbol 6012/Layer 2_20","x":972},{"width":40,"y":1046,"height":36,"name":"__dbTextures/Symbol 6012/Layer 2_37","x":849},{"width":40,"y":1084,"height":36,"name":"__dbTextures/Symbol 6012/Layer 2_47","x":975},{"frameY":0,"y":1236,"frameWidth":40,"frameX":0,"frameHeight":36,"width":39,"height":36,"name":"__dbTextures/Symbol 6012/Layer 2_6","x":890},{"width":40,"y":243,"height":36,"name":"__dbTextures/Symbol 6012/Layer 2_44","x":955},{"width":40,"y":479,"height":36,"name":"__dbTextures/Symbol 6012/Layer 2_45","x":945},{"frameY":0,"y":1198,"frameWidth":40,"frameX":0,"frameHeight":36,"width":39,"height":36,"name":"__dbTextures/Symbol 6012/Layer 2_2","x":931},{"width":40,"y":1122,"height":36,"name":"__dbTextures/Symbol 6012/Layer 2_3","x":849},{"frameY":0,"y":1274,"frameWidth":40,"frameX":0,"frameHeight":36,"width":39,"height":36,"name":"__dbTextures/Symbol 6012/Layer 2_1","x":849},{"width":40,"y":1122,"height":36,"name":"__dbTextures/Symbol 6012/Layer 2_31","x":891},{"width":40,"y":441,"height":36,"name":"__dbTextures/Symbol 6012/Layer 2_15","x":945},{"width":40,"y":743,"height":36,"name":"__dbTextures/Symbol 6012/Layer 2_13","x":919},{"frameY":0,"y":1198,"frameWidth":40,"frameX":0,"frameHeight":36,"width":39,"height":36,"name":"__dbTextures/Symbol 6012/Layer 2_18","x":849},{"frameY":0,"y":1312,"frameWidth":40,"frameX":0,"frameHeight":36,"width":39,"height":36,"name":"__dbTextures/Symbol 6012/Layer 2_48","x":924},{"width":40,"y":1409,"height":36,"name":"__dbTextures/Symbol 6012/Layer 2_29","x":278},{"frameY":0,"y":1289,"frameWidth":40,"frameX":0,"frameHeight":36,"width":39,"height":36,"name":"__dbTextures/Symbol 6012/Layer 2_19","x":637},{"width":40,"y":1008,"height":36,"name":"__dbTextures/Symbol 6012/Layer 2_28","x":891},{"width":40,"y":1122,"height":36,"name":"__dbTextures/Symbol 6012/Layer 2_36","x":933},{"width":40,"y":1084,"height":36,"name":"__dbTextures/Symbol 6012/Layer 2_49","x":933},{"width":40,"y":1160,"height":36,"name":"__dbTextures/Symbol 6012/Layer 2_30","x":891},{"width":40,"y":1409,"height":36,"name":"__dbTextures/Symbol 6012/Layer 2_41","x":362},{"frameY":0,"y":1289,"frameWidth":40,"frameX":0,"frameHeight":36,"width":39,"height":36,"name":"__dbTextures/Symbol 6012/Layer 2_8","x":719},{"width":40,"y":1046,"height":36,"name":"__dbTextures/Symbol 6012/Layer 2_25","x":933},{"width":40,"y":1008,"height":36,"name":"__dbTextures/Symbol 6012/Layer 2_40","x":933},{"frameY":0,"y":1236,"frameWidth":40,"frameX":0,"frameHeight":36,"width":39,"height":36,"name":"__dbTextures/Symbol 6012/Layer 2_4","x":931},{"frameY":0,"y":1198,"frameWidth":40,"frameX":0,"frameHeight":36,"width":39,"height":36,"name":"__dbTextures/Symbol 6012/Layer 2_35","x":972},{"width":40,"y":395,"height":36,"name":"__dbTextures/Symbol 6012/Layer 2_43","x":957},{"width":40,"y":1008,"height":36,"name":"__dbTextures/Symbol 6012/Layer 2_26","x":849},{"width":40,"y":319,"height":36,"name":"__dbTextures/Symbol 6012/Layer 2_42","x":955},{"width":40,"y":1160,"height":36,"name":"__dbTextures/Symbol 6012/Layer 2_17","x":849},{"frameY":0,"y":1312,"frameWidth":40,"frameX":0,"frameHeight":36,"width":39,"height":36,"name":"__dbTextures/Symbol 6012/Layer 2_0","x":883},{"width":40,"y":1046,"height":36,"name":"__dbTextures/Symbol 6012/Layer 2_32","x":891},{"frameY":0,"y":1198,"frameWidth":40,"frameX":0,"frameHeight":36,"width":39,"height":36,"name":"__dbTextures/Symbol 6012/Layer 2_21","x":890},{"frameY":0,"y":1289,"frameWidth":40,"frameX":0,"frameHeight":36,"width":39,"height":36,"name":"__dbTextures/Symbol 6012/Layer 2_7","x":801},{"width":40,"y":1160,"height":36,"name":"__dbTextures/Symbol 6012/Layer 2_10","x":933},{"frameY":0,"y":1236,"frameWidth":40,"frameX":0,"frameHeight":36,"width":39,"height":36,"name":"__dbTextures/Symbol 6012/Layer 2_5","x":849},{"frameY":0,"y":1160,"frameWidth":40,"frameX":0,"frameHeight":36,"width":39,"height":36,"name":"__dbTextures/Symbol 6012/Layer 2_11","x":975},{"width":40,"y":1122,"height":36,"name":"__dbTextures/Symbol 6012/Layer 2_23","x":975},{"width":40,"y":1046,"height":36,"name":"__dbTextures/Symbol 6012/Layer 2_27","x":975},{"frameY":0,"y":1312,"frameWidth":40,"frameX":0,"frameHeight":36,"width":39,"height":36,"name":"__dbTextures/Symbol 6012/Layer 2_34","x":842},{"width":40,"y":1084,"height":36,"name":"__dbTextures/Symbol 6012/Layer 2_39","x":891},{"width":40,"y":403,"height":36,"name":"__dbTextures/Symbol 6012/Layer 2_9","x":915},{"frameY":0,"y":1274,"frameWidth":40,"frameX":0,"frameHeight":36,"width":39,"height":36,"name":"__dbTextures/Symbol 6012/Layer 2_12","x":972},{"width":40,"y":357,"height":36,"name":"__dbTextures/Symbol 6012/Layer 2_46","x":955},{"width":22,"y":517,"height":22,"name":"__dbTextures/Symbol 6034/Layer 2_33","x":1001},{"width":23,"y":1597,"height":20,"name":"__dbTextures/Symbol 6034/Layer 2_17","x":993},{"width":24,"y":1588,"height":21,"name":"__dbTextures/Symbol 6034/Layer 2_21","x":642},{"width":22,"y":1596,"height":21,"name":"__dbTextures/Symbol 6034/Layer 2_36","x":969},{"width":22,"y":1574,"height":21,"name":"__dbTextures/Symbol 6034/Layer 2_29","x":995},{"width":24,"y":186,"height":21,"name":"__dbTextures/Symbol 6034/Layer 2_40","x":915},{"width":22,"y":1470,"height":21,"name":"__dbTextures/Symbol 6034/Layer 2_31","x":380},{"width":24,"y":1446,"height":21,"name":"__dbTextures/Symbol 6034/Layer 2_42","x":994},{"width":23,"y":1577,"height":21,"name":"__dbTextures/Symbol 6034/Layer 2_8","x":810},{"width":25,"y":1505,"height":21,"name":"__dbTextures/Symbol 6034/Layer 2_10","x":818},{"width":24,"y":1561,"height":21,"name":"__dbTextures/Symbol 6034/Layer 2_23","x":893},{"width":22,"y":1447,"height":21,"name":"__dbTextures/Symbol 6034/Layer 2_38","x":380},{"width":24,"y":1574,"height":20,"name":"__dbTextures/Symbol 6034/Layer 2_25","x":969},{"width":24,"y":1540,"height":21,"name":"__dbTextures/Symbol 6034/Layer 2_0","x":945},{"width":23,"y":1561,"height":21,"name":"__dbTextures/Symbol 6034/Layer 2_13","x":919},{"width":23,"y":1582,"height":20,"name":"__dbTextures/Symbol 6034/Layer 2_4","x":835},{"width":22,"y":1584,"height":20,"name":"__dbTextures/Symbol 6034/Layer 2_15","x":908},{"width":24,"y":1575,"height":21,"name":"__dbTextures/Symbol 6034/Layer 2_27","x":711},{"width":22,"y":1584,"height":20,"name":"__dbTextures/Symbol 6034/Layer 2_6","x":884},{"width":23,"y":1563,"height":21,"name":"__dbTextures/Symbol 6034/Layer 2_19","x":944},{"width":23,"y":1568,"height":21,"name":"__dbTextures/Symbol 6034/Layer 2_2","x":785},{"width":24,"y":209,"height":21,"name":"__dbTextures/Symbol 6034/Layer 2_44","x":915},{"width":40,"y":645,"height":40,"name":"__dbTextures/Symbol 6079/Layer 2_29","x":971},{"frameY":0,"y":433,"frameWidth":40,"frameX":-4,"frameHeight":40,"width":36,"height":40,"name":"__dbTextures/Symbol 6079/Layer 2_8","x":987},{"width":40,"y":918,"height":40,"name":"__dbTextures/Symbol 6079/Layer 2_30","x":912},{"frameY":-5,"y":1409,"frameWidth":40,"frameX":-3,"frameHeight":40,"width":29,"height":35,"name":"__dbTextures/Symbol 6079/Layer 2_9","x":994},{"frameY":0,"y":1498,"frameWidth":40,"frameX":-5,"frameHeight":40,"width":27,"height":28,"name":"__dbTextures/Symbol 6079/Layer 2_31","x":680},{"width":40,"y":911,"height":40,"name":"__dbTextures/Symbol 6079/Layer 2_10","x":954},{"frameY":0,"y":1435,"frameWidth":40,"frameX":0,"frameHeight":40,"width":40,"height":29,"name":"__dbTextures/Symbol 6079/Layer 2_32","x":812},{"width":40,"y":603,"height":40,"name":"__dbTextures/Symbol 6079/Layer 2_11","x":943},{"frameY":-1,"y":242,"frameWidth":40,"frameX":-6,"frameHeight":40,"width":26,"height":35,"name":"__dbTextures/Symbol 6079/Layer 2_33","x":997},{"width":40,"y":701,"height":40,"name":"__dbTextures/Symbol 6079/Layer 2_12","x":961},{"frameY":-1,"y":121,"frameWidth":40,"frameX":0,"frameHeight":40,"width":40,"height":39,"name":"__dbTextures/Symbol 6079/Layer 2_34","x":945},{"frameY":-2,"y":203,"frameWidth":40,"frameX":0,"frameHeight":40,"width":40,"height":38,"name":"__dbTextures/Symbol 6079/Layer 2_13","x":945},{"frameY":-1,"y":907,"frameWidth":40,"frameX":-6,"frameHeight":40,"width":26,"height":36,"name":"__dbTextures/Symbol 6079/Layer 2_35","x":996},{"frameY":-4,"y":1409,"frameWidth":40,"frameX":-9,"frameHeight":40,"width":24,"height":24,"name":"__dbTextures/Symbol 6079/Layer 2_14","x":717},{"frameY":-2,"y":869,"frameWidth":40,"frameX":-6,"frameHeight":40,"width":26,"height":36,"name":"__dbTextures/Symbol 6079/Layer 2_36","x":996},{"width":40,"y":701,"height":40,"name":"__dbTextures/Symbol 6079/Layer 2_15","x":919},{"frameY":-2,"y":545,"frameWidth":40,"frameX":-6,"frameHeight":40,"width":27,"height":36,"name":"__dbTextures/Symbol 6079/Layer 2_37","x":995},{"frameY":-1,"y":80,"frameWidth":40,"frameX":0,"frameHeight":40,"width":40,"height":39,"name":"__dbTextures/Symbol 6079/Layer 2_16","x":945},{"frameY":-1,"y":1381,"frameWidth":40,"frameX":-4,"frameHeight":40,"width":32,"height":39,"name":"__dbTextures/Symbol 6079/Layer 2_38","x":862},{"frameY":0,"y":603,"frameWidth":40,"frameX":-3,"frameHeight":40,"width":37,"height":40,"name":"__dbTextures/Symbol 6079/Layer 2_17","x":985},{"frameY":0,"y":165,"frameWidth":40,"frameX":0,"frameHeight":40,"width":35,"height":39,"name":"__dbTextures/Symbol 6079/Layer 2_39","x":987},{"frameY":-2,"y":457,"frameWidth":40,"frameX":-9,"frameHeight":40,"width":26,"height":38,"name":"__dbTextures/Symbol 6079/Layer 2_18","x":820},{"frameY":-6,"y":1466,"frameWidth":40,"frameX":0,"frameHeight":40,"width":34,"height":32,"name":"__dbTextures/Symbol 6079/Layer 2_40","x":845},{"frameY":-2,"y":1391,"frameWidth":40,"frameX":-9,"frameHeight":40,"width":31,"height":38,"name":"__dbTextures/Symbol 6079/Layer 2_19","x":896},{"frameY":-1,"y":162,"frameWidth":40,"frameX":0,"frameHeight":40,"width":40,"height":39,"name":"__dbTextures/Symbol 6079/Layer 2_41","x":945},{"frameY":-1,"y":1393,"frameWidth":40,"frameX":-8,"frameHeight":40,"width":29,"height":39,"name":"__dbTextures/Symbol 6079/Layer 2_20","x":929},{"frameY":-6,"y":1525,"frameWidth":40,"frameX":0,"frameHeight":40,"width":33,"height":28,"name":"__dbTextures/Symbol 6079/Layer 2_42","x":744},{"width":40,"y":785,"height":40,"name":"__dbTextures/Symbol 6079/Layer 2_21","x":964},{"width":40,"y":827,"height":40,"name":"__dbTextures/Symbol 6079/Layer 2_0","x":964},{"width":40,"y":869,"height":40,"name":"__dbTextures/Symbol 6079/Layer 2_43","x":954},{"frameY":-3,"y":1466,"frameWidth":40,"frameX":-8,"frameHeight":40,"width":31,"height":37,"name":"__dbTextures/Symbol 6079/Layer 2_22","x":812},{"width":40,"y":834,"height":40,"name":"__dbTextures/Symbol 6079/Layer 2_1","x":912},{"width":40,"y":876,"height":40,"name":"__dbTextures/Symbol 6079/Layer 2_23","x":912},{"frameY":0,"y":1536,"frameWidth":40,"frameX":-5,"frameHeight":40,"width":29,"height":30,"name":"__dbTextures/Symbol 6079/Layer 2_2","x":779},{"frameY":-1,"y":39,"frameWidth":40,"frameX":0,"frameHeight":40,"width":40,"height":39,"name":"__dbTextures/Symbol 6079/Layer 2_24","x":945},{"frameY":0,"y":1431,"frameWidth":40,"frameX":-5,"frameHeight":40,"width":29,"height":38,"name":"__dbTextures/Symbol 6079/Layer 2_3","x":888},{"frameY":-3,"y":1434,"frameWidth":40,"frameX":-9,"frameHeight":40,"width":31,"height":34,"name":"__dbTextures/Symbol 6079/Layer 2_25","x":919},{"frameY":0,"y":1367,"frameWidth":40,"frameX":-4,"frameHeight":40,"width":32,"height":40,"name":"__dbTextures/Symbol 6079/Layer 2_4","x":711},{"frameY":0,"y":38,"frameWidth":40,"frameX":-9,"frameHeight":40,"width":23,"height":28,"name":"__dbTextures/Symbol 6079/Layer 2_26","x":915},{"frameY":-2,"y":1353,"frameWidth":40,"frameX":-3,"frameHeight":40,"width":34,"height":38,"name":"__dbTextures/Symbol 6079/Layer 2_5","x":774},{"frameY":0,"y":1575,"frameWidth":40,"frameX":-8,"frameHeight":40,"width":29,"height":28,"name":"__dbTextures/Symbol 6079/Layer 2_27","x":680},{"frameY":-2,"y":363,"frameWidth":40,"frameX":0,"frameHeight":40,"width":38,"height":38,"name":"__dbTextures/Symbol 6079/Layer 2_6","x":915},{"width":40,"y":743,"height":40,"name":"__dbTextures/Symbol 6079/Layer 2_28","x":964},{"frameY":0,"y":39,"frameWidth":40,"frameX":-3,"frameHeight":40,"width":35,"height":40,"name":"__dbTextures/Symbol 6079/Layer 2_7","x":987}]}